kimimaro/__init__.py
kimimaro/intake.py
kimimaro/post.py
kimimaro/sharedmemory.py
kimimaro/skeletontricks.cpython-314-aarch64-linux-gnu.so
kimimaro/trace.py
kimimaro/utility.py
kimimaro_cli/__init__.py
kimimaro_cli/codecs.py
kimimaro-5.8.1.dist-info/METADATA
kimimaro-5.8.1.dist-info/WHEEL
kimimaro-5.8.1.dist-info/entry_points.txt
kimimaro-5.8.1.dist-info/top_level.txt
kimimaro-5.8.1.dist-info/RECORD
kimimaro-5.8.1.dist-info/licenses/AUTHORS
kimimaro-5.8.1.dist-info/licenses/LICENSE
