Metadata-Version: 2.4
Name: kimimaro
Version: 5.8.1
Summary: Skeletonize densely labeled image volumes.
Author: Alex Bae, Forrest Collman, Peter Li, Nina Shamsi
Author-email: William Silversmith <ws9@princeton.edu>
License: GPL-3.0-or-later
Project-URL: Homepage, https://github.com/seung-lab/kimimaro/
Keywords: volumetric-data,numpy,teasar,skeletonization,centerline,medial-axis-transform,centerline-extraction,computer-vision-algorithms,connectomics,image-processing,biomedical-image-processing,voxel
Classifier: Intended Audience :: Developers
Classifier: Development Status :: 5 - Production/Stable
Classifier: Programming Language :: Python
Classifier: Programming Language :: Python :: 3
Classifier: Programming Language :: Python :: 3.9
Classifier: Programming Language :: Python :: 3.10
Classifier: Programming Language :: Python :: 3.11
Classifier: Programming Language :: Python :: 3.12
Classifier: Programming Language :: Python :: 3.13
Classifier: Topic :: Scientific/Engineering
Classifier: Intended Audience :: Science/Research
Classifier: Operating System :: POSIX
Classifier: Operating System :: MacOS
Classifier: Operating System :: Microsoft :: Windows :: Windows 10
Requires-Python: <4.0.0,>=3.9.0
License-File: LICENSE
License-File: AUTHORS
Requires-Dist: click
Requires-Dist: connected-components-3d>=3.16.0
Requires-Dist: dijkstra3d>=1.15.0
Requires-Dist: fill-voids>=2.0.0
Requires-Dist: edt>=2.1.0
Requires-Dist: fastremap>=1.10.2
Requires-Dist: networkx
Requires-Dist: numpy>=1.16.1
Requires-Dist: osteoid
Requires-Dist: pathos
Requires-Dist: pytest
Requires-Dist: scipy>=1.1.0
Requires-Dist: tqdm
Requires-Dist: xs3d<2,>=1.2.0
Provides-Extra: accel
Requires-Dist: pykdtree; extra == "accel"
Provides-Extra: view
Requires-Dist: microviewer; extra == "view"
Requires-Dist: crackle-codec; extra == "view"
Requires-Dist: vtk; extra == "view"
Provides-Extra: tif
Requires-Dist: tifffile; extra == "tif"
Provides-Extra: nii
Requires-Dist: nibabel; extra == "nii"
Provides-Extra: nrrd
Requires-Dist: pynrrd; extra == "nrrd"
Provides-Extra: all-formats
Requires-Dist: tifffile; extra == "all-formats"
Requires-Dist: nibabel; extra == "all-formats"
Requires-Dist: pynrrd; extra == "all-formats"
Provides-Extra: all
Requires-Dist: tifffile; extra == "all"
Requires-Dist: nibabel; extra == "all"
Requires-Dist: pynrrd; extra == "all"
Requires-Dist: microviewer; extra == "all"
Requires-Dist: vtk; extra == "all"
Requires-Dist: pykdtree; extra == "all"
Dynamic: license-file
